{
  "pieces": [
    {
      "position": "c5",
      "type": "queen",
      "color": "white",
      "letter": "D"
    },
    {
      "position": "b4",
      "type": "knight",
      "color": "white",
      "letter": "H"
    },
    {
      "position": "d3",
      "type": "pawn",
      "color": "white",
      "letter": "L"
    },
    {
      "position": "e3",
      "type": "pawn",
      "color": "black",
      "letter": "R"
    },
    {
      "position": "c2",
      "type": "rook",
      "color": "white",
      "letter": "E"
    },
    {
      "position": "d2",
      "type": "bishop",
      "color": "white",
      "letter": "I"
    },
    {
      "position": "a1",
      "type": "knight",
      "color": "white",
      "letter": "O"
    },
    {
      "position": "d1",
      "type": "knight",
      "color": "white",
      "letter": "S"
    },
    {
      "position": "e1",
      "type": "knight",
      "color": "black",
      "letter": "L"
    }
  ],
  "targetWords": [
    "DRILL",
    "RILE",
    "RILL",
    "ILE",
    "ILL",
    "SRI"
  ],
  "targetPath": [
    "c5",
    "e3",
    "d2",
    "e1",
    "d3"
  ],
  "legalCaptures": {
    "c5": 1,
    "b4": 0,
    "d3": 0,
    "e3": 1,
    "c2": 0,
    "d2": 2,
    "a1": 0,
    "d1": 1,
    "e1": 2
  }
}