{
  "pieces": [
    {
      "position": "a5",
      "type": "pawn",
      "color": "black",
      "letter": "R"
    },
    {
      "position": "b5",
      "type": "knight",
      "color": "white",
      "letter": "E"
    },
    {
      "position": "c5",
      "type": "pawn",
      "color": "black",
      "letter": "R"
    },
    {
      "position": "d5",
      "type": "bishop",
      "color": "white",
      "letter": "T"
    },
    {
      "position": "e5",
      "type": "pawn",
      "color": "white",
      "letter": "T"
    },
    {
      "position": "d4",
      "type": "pawn",
      "color": "black",
      "letter": "E"
    },
    {
      "position": "a3",
      "type": "queen",
      "color": "white",
      "letter": "E"
    },
    {
      "position": "c3",
      "type": "rook",
      "color": "white",
      "letter": "Y"
    },
    {
      "position": "e3",
      "type": "knight",
      "color": "white",
      "letter": "D"
    },
    {
      "position": "b2",
      "type": "queen",
      "color": "black",
      "letter": "C"
    },
    {
      "position": "c2",
      "type": "pawn",
      "color": "black",
      "letter": "U"
    },
    {
      "position": "b1",
      "type": "queen",
      "color": "white",
      "letter": "C"
    },
    {
      "position": "c1",
      "type": "pawn",
      "color": "white",
      "letter": "F"
    },
    {
      "position": "e1",
      "type": "knight",
      "color": "white",
      "letter": "S"
    }
  ],
  "targetWords": [
    "SUCCEED",
    "EDUC",
    "CEE",
    "DUC",
    "EYR",
    "FCY"
  ],
  "targetPath": [
    "e1",
    "c2",
    "b1",
    "b2",
    "b5",
    "d4",
    "e3"
  ],
  "legalCaptures": {
    "a5": 0,
    "b5": 1,
    "c5": 0,
    "d5": 0,
    "e5": 0,
    "d4": 2,
    "a3": 3,
    "c3": 2,
    "e3": 1,
    "b2": 5,
    "c2": 1,
    "b1": 2,
    "c1": 1,
    "e1": 1
  }
}